LICENSE
MANIFEST.in
README.md
README.rst
git_del_br.py
setup.py
git_del_br.egg-info/PKG-INFO
git_del_br.egg-info/SOURCES.txt
git_del_br.egg-info/dependency_links.txt
git_del_br.egg-info/entry_points.txt
git_del_br.egg-info/top_level.txt