Metadata-Version: 1.1
Name: git-del-br
Version: 1.0.6
Summary: Git delete merged branches
Home-page: https://github.com/tusharmakkar08/git-del-br/
Author: Tushar Makkar
Author-email: tusharmakkar08@gmail.com
License: MIT
Platform: any
Classifier: Programming Language :: Python :: 2.7
